ecs_deploy/__init__.py
ecs_deploy/cli.py
ecs_deploy/deploy.py
python_ecs_deploy-0.0.4.dist-info/METADATA
python_ecs_deploy-0.0.4.dist-info/RECORD
python_ecs_deploy-0.0.4.dist-info/WHEEL
python_ecs_deploy-0.0.4.dist-info/entry_points.txt
python_ecs_deploy-0.0.4.dist-info/top_level.txt
python_ecs_deploy-0.0.4.dist-info/zip-safe
