Metadata-Version: 2.1
Name: python-ecs-deploy
Version: 0.0.4
Summary: This script use ecs client of boto3 to instigate an automatic blue/green deployment.
Home-page: https://github.com/qiqiming/python-ecs-deploy
Author: qiqiming
Author-email: tiedanqi@gmail.com
License: MIT
Keywords: python aws-ecs ecs
Platform: UNKNOWN
Classifier: Environment :: Console
Classifier: Intended Audience :: Developers
Classifier: License :: OSI Approved :: BSD License
Classifier: Operating System :: POSIX
Classifier: Operating System :: MacOS
Classifier: Operating System :: Unix
Classifier: Programming Language :: Python :: 3
Classifier: Topic :: Software Development :: Libraries :: Python Modules
Requires-Dist: boto3
